scipreprocess/__init__.py
scipreprocess/acronyms.py
scipreprocess/cli.py
scipreprocess/config.py
scipreprocess/features.py
scipreprocess/linking.py
scipreprocess/local_extract.py
scipreprocess/models.py
scipreprocess/parsers.py
scipreprocess/pipeline.py
scipreprocess/preprocessing.py
scipreprocess/sectioning.py
scipreprocess/utils.py
scipreprocess-0.1.2.dist-info/licenses/LICENSE
scipreprocess-0.1.2.dist-info/METADATA
scipreprocess-0.1.2.dist-info/WHEEL
scipreprocess-0.1.2.dist-info/top_level.txt
scipreprocess-0.1.2.dist-info/RECORD
