Metadata-Version: 2.4
Name: scipreprocess
Version: 0.1.2
Summary: A modular pipeline for preprocessing scientific documents (PDF, DOCX, TEX, XML, TXT)
Author-email: Tarikul Islam Anik <contact@oxyzen.dev>
License-Expression: MIT
Project-URL: Homepage, https://github.com/Tarikul-Islam-Anik/scipreprocess
Project-URL: Repository, https://github.com/Tarikul-Islam-Anik/scipreprocess
Project-URL: Documentation, https://github.com/Tarikul-Islam-Anik/scipreprocess#readme
Project-URL: Issues, https://github.com/Tarikul-Islam-Anik/scipreprocess/issues
Project-URL: Changelog, https://github.com/Tarikul-Islam-Anik/scipreprocess/blob/main/CHANGELOG.md
Keywords: scientific,preprocessing,nlp,pdf,documents
Classifier: Development Status :: 3 - Alpha
Classifier: Intended Audience :: Science/Research
Classifier: Programming Language :: Python :: 3
Classifier: Programming Language :: Python :: 3.10
Classifier: Programming Language :: Python :: 3.11
Classifier: Programming Language :: Python :: 3.12
Classifier: Topic :: Scientific/Engineering
Classifier: Topic :: Text Processing
Requires-Python: >=3.10
License-File: LICENSE
Requires-Dist: unidecode>=1.3.0
Requires-Dist: nameparser>=1.1.3
Provides-Extra: pdf
Requires-Dist: PyMuPDF>=1.23.0; extra == "pdf"
Provides-Extra: docx
Requires-Dist: python-docx>=0.8.11; extra == "docx"
Provides-Extra: xml
Requires-Dist: lxml>=4.9.0; extra == "xml"
Provides-Extra: ocr
Requires-Dist: opencv-python>=4.8.0; extra == "ocr"
Requires-Dist: pytesseract>=0.3.10; extra == "ocr"
Provides-Extra: nlp
Requires-Dist: nltk>=3.8.0; extra == "nlp"
Requires-Dist: spacy>=3.7.0; extra == "nlp"
Requires-Dist: scispacy>=0.5.0; extra == "nlp"
Requires-Dist: pysbd>=0.3.4; extra == "nlp"
Provides-Extra: ml
Requires-Dist: scikit-learn>=1.3.0; extra == "ml"
Requires-Dist: sentence-transformers>=2.2.0; extra == "ml"
Requires-Dist: faiss-cpu>=1.7.4; extra == "ml"
Provides-Extra: all
Requires-Dist: PyMuPDF>=1.23.0; extra == "all"
Requires-Dist: python-docx>=0.8.11; extra == "all"
Requires-Dist: lxml>=4.9.0; extra == "all"
Requires-Dist: opencv-python>=4.8.0; extra == "all"
Requires-Dist: pytesseract>=0.3.10; extra == "all"
Requires-Dist: nltk>=3.8.0; extra == "all"
Requires-Dist: spacy>=3.7.0; extra == "all"
Requires-Dist: scispacy>=0.5.0; extra == "all"
Requires-Dist: pysbd>=0.3.4; extra == "all"
Requires-Dist: scikit-learn>=1.3.0; extra == "all"
Requires-Dist: sentence-transformers>=2.2.0; extra == "all"
Requires-Dist: faiss-cpu>=1.7.4; extra == "all"
Provides-Extra: dev
Requires-Dist: pytest>=7.4.0; extra == "dev"
Requires-Dist: pytest-cov>=4.1.0; extra == "dev"
Requires-Dist: black>=23.0.0; extra == "dev"
Requires-Dist: ruff>=0.1.0; extra == "dev"
Requires-Dist: mypy>=1.5.0; extra == "dev"
Dynamic: license-file
